analysis_package/__init__.py
data_analysis_task_pkg_macca2707-0.0.2.dist-info/LICENSE
data_analysis_task_pkg_macca2707-0.0.2.dist-info/METADATA
data_analysis_task_pkg_macca2707-0.0.2.dist-info/WHEEL
data_analysis_task_pkg_macca2707-0.0.2.dist-info/top_level.txt
data_analysis_task_pkg_macca2707-0.0.2.dist-info/RECORD
