Metadata-Version: 2.1
Name: data-analysis-task-pkg-macca2707
Version: 0.0.2
Summary: Package containing analysis work for Halfbrick studios
Home-page: https://github.com/lm304/data-analyst-task.git
Author: Luke McGlashan
Author-email: lukemcglashan1998@gmail.com
License: UNKNOWN
Platform: UNKNOWN
Classifier: Programming Language :: Python :: 3
Classifier: License :: OSI Approved :: MIT License
Classifier: Operating System :: OS Independent
Requires-Python: >=3.6
